{
  "build_timestamp": "2025-09-27T09:37:50.032520",
  "library_version": "1.0.0",
  "library_hash": "4d86c08310c3b0ae83adfe78e9e153c5b022307bb9a9f83fb7ef2fed7e1cbbe9",
  "integration_version": "1.0.0",
  "validation_results": [
    {
      "check": "file_integrity",
      "status": "passed",
      "message": "All 13 files passed integrity check"
    },
    {
      "check": "manifest_structure",
      "status": "passed",
      "message": "Manifest structure validation passed"
    },
    {
      "check": "bundled_library",
      "status": "passed",
      "message": "Bundled library validation passed (40 files)"
    }
  ]
}